setup.py
OhMyChat_API/AI_GUI.py
OhMyChat_API/Get_API.py
OhMyChat_API/__init__.py
Zxy_Privated.egg-info/PKG-INFO
Zxy_Privated.egg-info/SOURCES.txt
Zxy_Privated.egg-info/dependency_links.txt
Zxy_Privated.egg-info/top_level.txt