Metadata-Version: 2.1
Name: Zxy_Privated
Version: 0.0.4
Summary: 需要到 https://aigptx.top/ 注册并获取api秘钥(废弃),使用秋雨所写的chatGPT3接口
Home-page: https://github.com/
Author: AnQing
Classifier: Programming Language :: Python :: 3
Classifier: License :: OSI Approved :: MIT License
Classifier: Operating System :: OS Independent
